{
    "工廠名稱": "桀芈企業有限公司",
    "工廠登記編號": "03002642",
    "工廠設立許可案號": "",
    "工廠地址": "桃園市蘆竹區中福里龍壽街一段267號",
    "工廠市鎮鄉村里": "桃園市蘆竹區中福里",
    "工廠負責人姓名": "陳謙德",
    "營利事業統一編號": "54506414",
    "工廠組織型態": "有限公司",
    "工廠設立核准日期": "",
    "工廠登記核准日期": "1031229",
    "工廠登記狀態": "生產中",
    "產業類別": [
        "25金屬製品製造業"
    ],
    "主要產品": [
        "259其他金屬製品"
    ],
    "egis": {
        "AddrOrg": "桃園市蘆竹區中福里龍壽街一段２６７號",
        "FactoryID": "03002642",
        "FactoryName": "桀?企業有限公司",
        "faxno": "03-3237177",
        "IndustryClass": "未分類其他金屬製品製造業(2599)",
        "IndustryClass2": "金屬製品製造業(25)",
        "material": "",
        "plantrep": "陳謙德",
        "prodname": "其他金屬製品",
        "telno": "03-3237979",
        "web": "www.cpsfastener.com",
        "X": "276900.05",
        "Y": "2765240.99"
    }
}