{
    "工廠名稱": "連宏企業社",
    "工廠登記編號": "07001340",
    "工廠設立許可案號": "",
    "工廠地址": "彰化縣和美鎮山犁里仁和路80號",
    "工廠市鎮鄉村里": "彰化縣和美鎮山犁里",
    "工廠負責人姓名": "周詩穎",
    "營利事業統一編號": "39949397",
    "工廠組織型態": "獨資",
    "工廠設立核准日期": "",
    "工廠登記核准日期": "1031027",
    "工廠登記狀態": "生產中",
    "產業類別": [
        "11紡織業"
    ],
    "主要產品": [
        "111紡紗"
    ],
    "egis": {
        "AddrOrg": "彰化縣和美鎮山犁里仁和路８０號",
        "FactoryID": "07001340",
        "FactoryName": "連宏企業社",
        "faxno": "",
        "IndustryClass": "人造纖維紡紗業(1112)",
        "IndustryClass2": "紡織業(11)",
        "material": "",
        "plantrep": "周詩穎",
        "prodname": "紡紗",
        "telno": "04-7566142",
        "web": "",
        "X": "198715.36",
        "Y": "2666950.33"
    }
}