{
    "工廠名稱": "一山環保工程開發有限公司嘉太廠",
    "工廠登記編號": "10000123",
    "工廠設立許可案號": "",
    "工廠地址": "嘉義縣太保市過溝里嘉太工業區光復路6號",
    "工廠市鎮鄉村里": "嘉義縣太保市過溝里",
    "工廠負責人姓名": "柯世苑",
    "營利事業統一編號": "80719882",
    "工廠組織型態": "有限公司",
    "工廠設立核准日期": "",
    "工廠登記核准日期": "1020923",
    "工廠登記狀態": "生產中",
    "產業類別": [
        "18化學材料製造業"
    ],
    "主要產品": [
        "181基本化學材料"
    ],
    "egis": {
        "AddrOrg": "嘉義縣太保市過溝里嘉太工業區光復路６號",
        "FactoryID": "10000123",
        "FactoryName": "一山環保工程開發有限公司嘉太廠",
        "faxno": "",
        "IndustryClass": "基本化學材料製造業(1810)",
        "IndustryClass2": "化學材料製造業(18)",
        "material": "",
        "plantrep": "柯世苑",
        "prodname": "多元醇",
        "telno": "",
        "web": "",
        "X": "184990.08",
        "Y": "2600471.71"
    }
}