{
    "工廠名稱": "鼎城工業社",
    "工廠登記編號": "T0700034",
    "工廠設立許可案號": "",
    "工廠地址": "彰化縣埔心鄉太平村太平路310巷6號",
    "工廠市鎮鄉村里": "彰化縣埔心鄉太平村",
    "工廠負責人姓名": "張文縣",
    "營利事業統一編號": "80813514",
    "工廠組織型態": "獨資",
    "工廠設立核准日期": "",
    "工廠登記核准日期": "1010403",
    "工廠登記狀態": "生產中",
    "產業類別": [
        "30汽車及其零件製造業"
    ],
    "主要產品": [
        "303汽車零件"
    ],
    "egis": {
        "AddrOrg": "彰化縣埔心鄉太平村太平路３１０巷６號",
        "FactoryID": "T0700034",
        "FactoryName": "鼎城工業社",
        "faxno": "",
        "IndustryClass": "汽車零件製造業(3030)",
        "IndustryClass2": "汽車及其零件製造業(30)",
        "material": "",
        "plantrep": "張文縣",
        "prodname": "其他金屬製品、汽車及其零件、機車及其零件",
        "telno": "",
        "web": "",
        "X": "204480.22",
        "Y": "2648455.08"
    }
}