{
    "工廠名稱": "玄鐘實業有限公司",
    "工廠登記編號": "T1300039",
    "工廠設立許可案號": "",
    "工廠地址": "屏東縣萬丹鄉竹林村大學路三號",
    "工廠市鎮鄉村里": "屏東縣萬丹鄉竹林村",
    "工廠負責人姓名": "蔡煥清",
    "營利事業統一編號": "89267831",
    "工廠組織型態": "有限公司",
    "工廠設立核准日期": "",
    "工廠登記核准日期": "1021104",
    "工廠登記狀態": "生產中",
    "產業類別": [
        "25金屬製品製造業"
    ],
    "主要產品": [
        "252金屬結構及建築組件"
    ],
    "egis": {
        "AddrOrg": "屏東縣萬丹鄉竹林村大學路３號",
        "FactoryID": "T1300039",
        "FactoryName": "玄鐘實業有限公司",
        "faxno": "",
        "IndustryClass": "其他金屬加工處理業(2549)",
        "IndustryClass2": "金屬製品製造業(25)",
        "material": "",
        "plantrep": "蔡煥清",
        "prodname": "鋼皮加工",
        "telno": "",
        "web": "",
        "X": "200753.50",
        "Y": "2499890.08"
    }
}