{
    "工廠名稱": "加美服裝行",
    "工廠登記編號": "T6500176",
    "工廠設立許可案號": "",
    "工廠地址": "新北市板橋區文化路1段270巷30號2、3樓",
    "工廠市鎮鄉村里": "新北市板橋區",
    "工廠負責人姓名": "史鄭鍊",
    "營利事業統一編號": "15962721",
    "工廠組織型態": "獨資",
    "工廠設立核准日期": "",
    "工廠登記核准日期": "1010824",
    "工廠登記狀態": "生產中",
    "產業類別": [
        "12成衣及服飾品製造業"
    ],
    "主要產品": [
        "121梭織成衣"
    ],
    "egis": {
        "AddrOrg": "新北市板橋區文化路一段２７０巷３０號２、３樓",
        "FactoryID": "T6500176",
        "FactoryName": "加美服裝行",
        "faxno": "",
        "IndustryClass": "梭織外衣製造業(1211)",
        "IndustryClass2": "成衣及服飾品製造業(12)",
        "material": "",
        "plantrep": "鄭史瑜",
        "prodname": "褲子",
        "telno": "",
        "web": "",
        "X": "297235.72",
        "Y": "2768110.54"
    }
}