{
    "工廠名稱": "銘吉企業有限公司",
    "工廠登記編號": "99603448",
    "工廠設立許可案號": "07810001345342",
    "工廠地址": "新北市新莊區中正路五五八之二七號",
    "工廠市鎮鄉村里": "新北市新莊區",
    "工廠負責人姓名": "林鳳英",
    "營利事業統一編號": "22125911",
    "工廠組織型態": "有限公司",
    "工廠設立核准日期": "0781116",
    "工廠登記核准日期": "0781205",
    "工廠登記狀態": "生產中",
    "產業類別": [
        "25金屬製品製造業",
        "28電力設備製造業",
        "29機械設備製造業"
    ],
    "主要產品": [
        "251金屬手工具及模具",
        "259其他金屬製品",
        "285家用電器",
        "292其他專用機械設備",
        "293通用機械設備"
    ],
    "egis": {
        "AddrOrg": "新北市新莊區中正路５５８之２７號",
        "FactoryID": "99603448",
        "FactoryName": "銘吉企業有限公司",
        "faxno": "",
        "IndustryClass": "金屬家具製造業(3220)",
        "IndustryClass2": "家具製造業(32)",
        "material": "",
        "plantrep": "林鳳英",
        "prodname": "各種不銹鋼廚房調理機具",
        "telno": "",
        "web": "",
        "X": "293221.83",
        "Y": "2769425.92"
    }
}