{
    "工廠名稱": "瑞聯興業股份有限公司",
    "工廠登記編號": "99607995",
    "工廠設立許可案號": "08310001444441",
    "工廠地址": "新北市汐止區新臺五路一段七七號一三樓之八",
    "工廠市鎮鄉村里": "新北市汐止區",
    "工廠負責人姓名": "楊忠憲",
    "營利事業統一編號": "20970525",
    "工廠組織型態": "股份有限公司",
    "工廠設立核准日期": "0840107",
    "工廠登記核准日期": "0840118",
    "工廠登記狀態": "生產中",
    "產業類別": [
        "28電力設備製造業",
        "32家具製造業"
    ],
    "主要產品": [
        "281發電、輸電、配電機械",
        "283電線及配線器材",
        "284照明設備",
        "285家用電器",
        "289其他電力設備",
        "322金屬家具"
    ],
    "egis": {
        "AddrOrg": "新北市汐止區新臺五路一段７７號１３樓之８",
        "FactoryID": "99607995",
        "FactoryName": "瑞聯興業股份有限公司",
        "faxno": "",
        "IndustryClass": "調味品製造業(0896)",
        "IndustryClass2": "食品製造業(08)",
        "material": "",
        "plantrep": "楊忠憲",
        "prodname": "調味品、香料",
        "telno": "",
        "web": "",
        "X": "315082.32",
        "Y": "2772732.88"
    }
}