{
    "工廠名稱": "和毅工業有限公司",
    "工廠登記編號": "99608716",
    "工廠設立許可案號": "07410001231293",
    "工廠地址": "新北市三重區中正北路五０八巷三七號",
    "工廠市鎮鄉村里": "新北市三重區",
    "工廠負責人姓名": "林里松",
    "營利事業統一編號": "36110966",
    "工廠組織型態": "有限公司",
    "工廠設立核准日期": "0740821",
    "工廠登記核准日期": "0740914",
    "工廠登記狀態": "生產中",
    "產業類別": [
        "25金屬製品製造業",
        "29機械設備製造業"
    ],
    "主要產品": [
        "251金屬手工具及模具",
        "292其他專用機械設備",
        "293通用機械設備"
    ],
    "egis": {
        "AddrOrg": "新北市三重區中正北路５０８巷３７號",
        "FactoryID": "99608716",
        "FactoryName": "和毅工業有限公司",
        "faxno": "",
        "IndustryClass": "機械傳動設備製造業(2934)",
        "IndustryClass2": "機械設備製造業(29)",
        "material": "",
        "plantrep": "林里松",
        "prodname": "減速機",
        "telno": "",
        "web": "",
        "X": "297673.11",
        "Y": "2773662.85"
    }
}