{
    "工廠名稱": "天寶有限公司",
    "工廠登記編號": "99601326",
    "工廠設立許可案號": "08910001313241",
    "工廠地址": "新北市汐止區福德一路四五三號",
    "工廠市鎮鄉村里": "新北市汐止區",
    "工廠負責人姓名": "宋寧岡",
    "營利事業統一編號": "21237071",
    "工廠組織型態": "有限公司",
    "工廠設立核准日期": "0891012",
    "工廠登記核准日期": "0891122",
    "工廠登記狀態": "生產中",
    "產業類別": [
        "19化學製品製造業"
    ],
    "主要產品": [
        "199其他化學製品"
    ],
    "egis": {
        "AddrOrg": "新北市汐止區福德一路４５３號",
        "FactoryID": "99601326",
        "FactoryName": "天寶有限公司",
        "faxno": "",
        "IndustryClass": "其他化學製品製造業(1990)",
        "IndustryClass2": "化學製品製造業(19)",
        "material": "",
        "plantrep": "宋寧岡",
        "prodname": "ＬＥＤ封膠",
        "telno": "",
        "web": "",
        "X": "313154.57",
        "Y": "2772460.80"
    }
}