{
    "工廠名稱": "光陽工業股份有限公司五股廠",
    "工廠登記編號": "99601761",
    "工廠設立許可案號": "08210000084684",
    "工廠地址": "新北市五股區五工六路二七號",
    "工廠市鎮鄉村里": "新北市五股區",
    "工廠負責人姓名": "柯勝峯",
    "營利事業統一編號": "75195800",
    "工廠組織型態": "股份有限公司",
    "工廠設立核准日期": "0821027",
    "工廠登記核准日期": "0830216",
    "工廠登記狀態": "生產中",
    "產業類別": [
        "31其他運輸工具及其零件製造業"
    ],
    "主要產品": [
        "312機車及其零件"
    ],
    "egis": {
        "AddrOrg": "新北市五股區五工六路２７號",
        "FactoryID": "99601761",
        "FactoryName": "光陽工業股份有限公司五股廠",
        "faxno": "07-3840112",
        "IndustryClass": "汽車製造業(3010)",
        "IndustryClass2": "汽車及其零件製造業(30)",
        "material": "",
        "plantrep": "柯勝?",
        "prodname": "機車引擎另件",
        "telno": "02-22988975",
        "web": "www.kymco.com.tw",
        "X": "295253.66",
        "Y": "2772865.79"
    }
}