{
    "工廠名稱": "建邦銀樓有限公司",
    "工廠登記編號": "99611984",
    "工廠設立許可案號": "07610001185900",
    "工廠地址": "新北市三重區自強路四段三巷一三號",
    "工廠市鎮鄉村里": "新北市三重區",
    "工廠負責人姓名": "張平華",
    "營利事業統一編號": "22060516",
    "工廠組織型態": "有限公司",
    "工廠設立核准日期": "0760630",
    "工廠登記核准日期": "0760930",
    "工廠登記狀態": "生產中",
    "產業類別": [
        "25金屬製品製造業",
        "29機械設備製造業"
    ],
    "主要產品": [
        "259其他金屬製品",
        "293通用機械設備"
    ],
    "egis": {
        "AddrOrg": "新北市三重區自強路四段３巷１３號",
        "FactoryID": "99611984",
        "FactoryName": "建邦銀樓有限公司",
        "faxno": "02-22868397",
        "IndustryClass": "其他未分類製造業(3399)",
        "IndustryClass2": "其他製造業(33)",
        "material": "",
        "plantrep": "張平華",
        "prodname": "金銀銅飾品",
        "telno": "02-22867351",
        "web": "",
        "X": "299351.59",
        "Y": "2774304.51"
    }
}