{
    "工廠名稱": "鑫械汽車有限公司",
    "工廠登記編號": "99616245",
    "工廠設立許可案號": "08110001047924",
    "工廠地址": "新北市新莊區新樹路八號",
    "工廠市鎮鄉村里": "新北市新莊區",
    "工廠負責人姓名": "鄧建宇",
    "營利事業統一編號": "80609457",
    "工廠組織型態": "有限公司",
    "工廠設立核准日期": "0810309",
    "工廠登記核准日期": "0810422",
    "工廠登記狀態": "生產中",
    "產業類別": [
        "25金屬製品製造業",
        "29機械設備製造業",
        "30汽車及其零件製造業"
    ],
    "主要產品": [
        "259其他金屬製品",
        "293通用機械設備",
        "303汽車零件"
    ],
    "egis": {
        "AddrOrg": "新北市新莊區新樹路８號",
        "FactoryID": "99616245",
        "FactoryName": "鑫械汽車有限公司",
        "faxno": "",
        "IndustryClass": "其他通用機械設備製造業(2939)",
        "IndustryClass2": "機械設備製造業(29)",
        "material": "",
        "plantrep": "鄧旺城",
        "prodname": "機械零件",
        "telno": "",
        "web": "",
        "X": "294489.47",
        "Y": "2769518.92"
    }
}