{
    "工廠名稱": "翔昌鍋爐有限公司",
    "工廠登記編號": "99620787",
    "工廠設立許可案號": "",
    "工廠地址": "宜蘭縣蘇澳鎮德興六路五之一號",
    "工廠市鎮鄉村里": "宜蘭縣蘇澳鎮",
    "工廠負責人姓名": "洪忠發　　　",
    "營利事業統一編號": "84211346",
    "工廠組織型態": "有限公司",
    "工廠設立核准日期": "",
    "工廠登記核准日期": "0850624",
    "工廠登記狀態": "生產中",
    "產業類別": [
        "25金屬製品製造業"
    ],
    "主要產品": [
        "259其他金屬製品"
    ],
    "egis": {
        "AddrOrg": "宜蘭縣蘇澳鎮德興六路５之１號",
        "FactoryID": "99620787",
        "FactoryName": "翔昌鍋爐有限公司",
        "faxno": "",
        "IndustryClass": "鍋爐、金屬貯槽及壓力容器製造業(2531)",
        "IndustryClass2": "金屬製品製造業(25)",
        "material": "",
        "plantrep": "洪忠發",
        "prodname": "鍋爐",
        "telno": "",
        "web": "",
        "X": "333521.93",
        "Y": "2725171.78"
    }
}