{
    "工廠名稱": "新竹縣芎林鄉農會碾米廠",
    "工廠登記編號": "99630078",
    "工廠設立許可案號": "06810000127235",
    "工廠地址": "新竹縣芎林鄉上山村文山路６２６號",
    "工廠市鎮鄉村里": "新竹縣芎林鄉上山村",
    "工廠負責人姓名": "鍾文烈",
    "營利事業統一編號": "48055600",
    "工廠組織型態": "農會組織",
    "工廠設立核准日期": "0580101",
    "工廠登記核准日期": "0690723",
    "工廠登記狀態": "生產中",
    "產業類別": [
        "08食品製造業"
    ],
    "主要產品": [
        "089其他食品"
    ],
    "egis": {
        "AddrOrg": "新竹縣芎林鄉上山村文山路６２６號",
        "FactoryID": "99630078",
        "FactoryName": "新竹縣芎林鄉農會碾米廠",
        "faxno": "",
        "IndustryClass": "碾榖業(0861)",
        "IndustryClass2": "食品製造業(08)",
        "material": "",
        "plantrep": "鍾文烈",
        "prodname": "糙米農糧署委託業務",
        "telno": "",
        "web": "",
        "X": "257728.54",
        "Y": "2741368.56"
    }
}