{
    "工廠名稱": "愛瑪瑞實業股份有限公司大里廠",
    "工廠登記編號": "99637078",
    "工廠設立許可案號": "",
    "工廠地址": "臺中市大里區仁化里仁化路692號",
    "工廠市鎮鄉村里": "臺中市大里區仁化里",
    "工廠負責人姓名": "廖勝揮",
    "營利事業統一編號": "23153415",
    "工廠組織型態": "股份有限公司",
    "工廠設立核准日期": "",
    "工廠登記核准日期": "0910731",
    "工廠登記狀態": "生產中",
    "產業類別": [
        "28電力設備製造業"
    ],
    "主要產品": [
        "284照明設備"
    ],
    "egis": {
        "AddrOrg": "臺中市大里區仁化里仁化路６９２號",
        "FactoryID": "99637078",
        "FactoryName": "愛瑪瑞實業股份有限公司大里廠",
        "faxno": "",
        "IndustryClass": "電燈泡及燈管製造業(2841)",
        "IndustryClass2": "電力設備製造業(28)",
        "material": "",
        "plantrep": "廖勝揮",
        "prodname": "家電設備",
        "telno": "",
        "web": "www.bosswell.asia",
        "X": "218836.26",
        "Y": "2665502.46"
    }
}