{
    "工廠名稱": "亞洲水泥股份有限公司新竹製造廠",
    "工廠登記編號": "99630250",
    "工廠設立許可案號": "05810000001229",
    "工廠地址": "新竹縣橫山鄉大肚村中豐路二段109號",
    "工廠市鎮鄉村里": "新竹縣橫山鄉大肚村",
    "工廠負責人姓名": "邱志宏 ",
    "營利事業統一編號": "03244509",
    "工廠組織型態": "股份有限公司",
    "工廠設立核准日期": "0580101",
    "工廠登記核准日期": "0581027",
    "工廠登記狀態": "生產中",
    "產業類別": [
        "23非金屬礦物製品製造業"
    ],
    "主要產品": [
        "233水泥及其製品"
    ],
    "egis": {
        "AddrOrg": "新竹縣橫山鄉大肚村中豐路二段１０９號",
        "FactoryID": "99630250",
        "FactoryName": "亞洲水泥股份有限公司新竹製造廠",
        "faxno": "03-5932837",
        "IndustryClass": "水泥製造業(2331)",
        "IndustryClass2": "非金屬礦物製品製造業(23)",
        "material": "",
        "plantrep": "邱志宏",
        "prodname": "水泥與熟料",
        "telno": "03-5931011",
        "web": "",
        "X": "263826.87",
        "Y": "2735040.57"
    }
}