{
    "工廠名稱": "巨庭機械股份有限公司二廠",
    "工廠登記編號": "99633653",
    "工廠設立許可案號": "08710006244175",
    "工廠地址": "臺中市太平區太平里永成路八０號",
    "工廠市鎮鄉村里": "臺中市太平區太平里",
    "工廠負責人姓名": "莊博彥",
    "營利事業統一編號": "52646207",
    "工廠組織型態": "股份有限公司",
    "工廠設立核准日期": "0870921",
    "工廠登記核准日期": "0891113",
    "工廠登記狀態": "生產中",
    "產業類別": [
        "29機械設備製造業"
    ],
    "主要產品": [
        "292其他專用機械設備"
    ],
    "egis": {
        "AddrOrg": "臺中市太平區太平里永成路８０號",
        "FactoryID": "99633653",
        "FactoryName": "巨庭機械股份有限公司二廠",
        "faxno": "04-22702699",
        "IndustryClass": "金屬切削工具機製造業(2912)",
        "IndustryClass2": "機械設備製造業(29)",
        "material": "鋼材、鐵材、板金",
        "plantrep": "莊博彥",
        "prodname": "木工機",
        "telno": "04-22792345",
        "web": "www.geetech.com.tw",
        "X": "220480.65",
        "Y": "2667871.45"
    }
}