{
    "工廠名稱": "竣威科技股份有限公司",
    "工廠登記編號": "99630798",
    "工廠設立許可案號": "08910004307672",
    "工廠地址": "新竹縣竹東鎮頭重里中興路四段８３０號３樓",
    "工廠市鎮鄉村里": "新竹縣竹東鎮頭重里",
    "工廠負責人姓名": "林佩璇",
    "營利事業統一編號": "12603126",
    "工廠組織型態": "股份有限公司",
    "工廠設立核准日期": "0891211",
    "工廠登記核准日期": "0900103",
    "工廠登記狀態": "生產中",
    "產業類別": [
        "26電子零組件製造業"
    ],
    "主要產品": [
        "262被動電子元件"
    ],
    "egis": {
        "AddrOrg": "新竹縣竹東鎮頭重里中興路四段８３０號３樓",
        "FactoryID": "99630798",
        "FactoryName": "竣威科技股份有限公司",
        "faxno": "",
        "IndustryClass": "被動電子元件製造業(2620)",
        "IndustryClass2": "電子零組件製造業(26)",
        "material": "",
        "plantrep": "林佩璇",
        "prodname": "晶片電阻、電阻膠、導電膠",
        "telno": "",
        "web": "",
        "X": "253288.80",
        "Y": "2741180.76"
    }
}