{
    "工廠名稱": "富田製藥廠股份有限公司",
    "工廠登記編號": "99645474",
    "工廠設立許可案號": "08210000081306",
    "工廠地址": "彰化縣伸港鄉溪底村興工路四三號",
    "工廠市鎮鄉村里": "彰化縣伸港鄉溪底村",
    "工廠負責人姓名": "黃周雪鳳",
    "營利事業統一編號": "86955807",
    "工廠組織型態": "股份有限公司",
    "工廠設立核准日期": "0820128",
    "工廠登記核准日期": "0830615",
    "工廠登記狀態": "生產中",
    "產業類別": [
        "20藥品及醫用化學製品製造業"
    ],
    "主要產品": [
        "200藥品及醫用化學製品"
    ],
    "egis": {
        "AddrOrg": "彰化縣伸港鄉溪底村興工路４３號",
        "FactoryID": "99645474",
        "FactoryName": "富田製藥廠股份有限公司",
        "faxno": "",
        "IndustryClass": "中藥製造業(2004)",
        "IndustryClass2": "藥品及醫用化學製品製造業(20)",
        "material": "",
        "plantrep": "黃周雪鳳",
        "prodname": "中藥濃縮製劑",
        "telno": "04-7989696",
        "web": "www.futian.com.tw",
        "X": "200296.98",
        "Y": "2673303.89"
    }
}