{
    "工廠名稱": "旺承工業有限公司",
    "工廠登記編號": "99641876",
    "工廠設立許可案號": "",
    "工廠地址": "臺中市大里區瑞城里塗城路304巷28弄18-2號",
    "工廠市鎮鄉村里": "臺中市大里區瑞城里",
    "工廠負責人姓名": "劉俊明",
    "營利事業統一編號": "80119775",
    "工廠組織型態": "有限公司",
    "工廠設立核准日期": "",
    "工廠登記核准日期": "0920224",
    "工廠登記狀態": "生產中",
    "產業類別": [
        "22塑膠製品製造業",
        "25金屬製品製造業"
    ],
    "主要產品": [
        "220塑膠製品",
        "251金屬手工具及模具"
    ],
    "egis": {
        "AddrOrg": "臺中市大里區瑞城里塗城路３０４巷２８弄１８之２號",
        "FactoryID": "99641876",
        "FactoryName": "旺承工業有限公司",
        "faxno": "",
        "IndustryClass": "其他塑膠製品製造業(2209)",
        "IndustryClass2": "塑膠製品製造業(22)",
        "material": "",
        "plantrep": "劉俊明",
        "prodname": "塑膠製品",
        "telno": "04-24965956",
        "web": "",
        "X": "220283.71",
        "Y": "2664853.10"
    }
}