{
    "工廠名稱": "源泰鑄造股份有限公司",
    "工廠登記編號": "99642081",
    "工廠設立許可案號": "07310006054591",
    "工廠地址": "臺中市太平區東汴里長龍路三段二四五巷五號",
    "工廠市鎮鄉村里": "臺中市太平區東汴里",
    "工廠負責人姓名": "廖俊豪",
    "營利事業統一編號": "22601837",
    "工廠組織型態": "股份有限公司",
    "工廠設立核准日期": "0730416",
    "工廠登記核准日期": "0730830",
    "工廠登記狀態": "生產中",
    "產業類別": [
        "29機械設備製造業"
    ],
    "主要產品": [
        "293通用機械設備"
    ],
    "egis": {
        "AddrOrg": "臺中市太平區東汴里長龍路三段２４５巷５號",
        "FactoryID": "99642081",
        "FactoryName": "源泰鑄造股份有限公司",
        "faxno": "04-22775830",
        "IndustryClass": "汽車零件製造業(3030)",
        "IndustryClass2": "汽車及其零件製造業(30)",
        "material": "",
        "plantrep": "廖俊豪",
        "prodname": "機械零件",
        "telno": "",
        "web": "",
        "X": "226934.51",
        "Y": "2666690.59"
    }
}