{
    "工廠名稱": "鉅豐鐵工廠股份有限公司",
    "工廠登記編號": "99642048",
    "工廠設立許可案號": "07710006068939",
    "工廠地址": "臺中市豐原區鐮村里鎌村路四七二巷六三之一號",
    "工廠市鎮鄉村里": "臺中市豐原區",
    "工廠負責人姓名": "陳裕仁",
    "營利事業統一編號": "22712593",
    "工廠組織型態": "股份有限公司",
    "工廠設立核准日期": "0770505",
    "工廠登記核准日期": "0770516",
    "工廠登記狀態": "生產中",
    "產業類別": [
        "29機械設備製造業"
    ],
    "主要產品": [
        "293通用機械設備"
    ],
    "egis": {
        "AddrOrg": "臺中市豐原區鐮村里鎌村路４７２巷６３之１號",
        "FactoryID": "99642048",
        "FactoryName": "鉅豐鐵工廠股份有限公司",
        "faxno": "",
        "IndustryClass": "其他通用機械設備製造業(2939)",
        "IndustryClass2": "機械設備製造業(29)",
        "material": "",
        "plantrep": "陳裕仁",
        "prodname": "零件",
        "telno": "",
        "web": "",
        "X": "221928.54",
        "Y": "2679905.31"
    }
}