{
    "工廠名稱": "豐順紡織股份有限公司",
    "工廠登記編號": "99648971",
    "工廠設立許可案號": "06210000086202",
    "工廠地址": "彰化縣和美鎮竹營里孝義路１３２號",
    "工廠市鎮鄉村里": "彰化縣和美鎮竹營里",
    "工廠負責人姓名": "洪成德　　　",
    "營利事業統一編號": "59019624",
    "工廠組織型態": "股份有限公司",
    "工廠設立核准日期": "0580101",
    "工廠登記核准日期": "0630418",
    "工廠登記狀態": "生產中",
    "產業類別": [
        "11紡織業"
    ],
    "主要產品": [
        "112織布"
    ],
    "egis": {
        "AddrOrg": "彰化縣和美鎮竹營里孝義路１３２號",
        "FactoryID": "99648971",
        "FactoryName": "豐順紡織股份有限公司",
        "faxno": "",
        "IndustryClass": "棉、毛梭織布業(1121)",
        "IndustryClass2": "紡織業(11)",
        "material": "",
        "plantrep": "洪成德",
        "prodname": "棉布、混紡布",
        "telno": "",
        "web": "",
        "X": "200262.18",
        "Y": "2667743.26"
    }
}