{
    "工廠名稱": "茗溢金屬有限公司",
    "工廠登記編號": "99647970",
    "工廠設立許可案號": "08710007187636",
    "工廠地址": "彰化縣大村鄉大橋村中山路３段５７巷２０弄７號",
    "工廠市鎮鄉村里": "彰化縣大村鄉",
    "工廠負責人姓名": "李王也　",
    "營利事業統一編號": "16399461",
    "工廠組織型態": "有限公司",
    "工廠設立核准日期": "0871022",
    "工廠登記核准日期": "0890925",
    "工廠登記狀態": "生產中",
    "產業類別": [
        "25金屬製品製造業"
    ],
    "主要產品": [
        "254金屬加工處理"
    ],
    "egis": {
        "AddrOrg": "彰化縣大村鄉大橋村中山路三段５７巷２０弄７號",
        "FactoryID": "99647970",
        "FactoryName": "茗溢金屬有限公司",
        "faxno": "",
        "IndustryClass": "金屬表面處理業(2544)",
        "IndustryClass2": "金屬製品製造業(25)",
        "material": "",
        "plantrep": "李王也",
        "prodname": "電鍍",
        "telno": "04-8532127",
        "web": "",
        "X": "205190.12",
        "Y": "2654480.47"
    }
}