{
    "工廠名稱": "田園股份有限公司",
    "工廠登記編號": "99654524",
    "工廠設立許可案號": "08110009109245",
    "工廠地址": "雲林縣北港鎮番溝里番溝五○號",
    "工廠市鎮鄉村里": "雲林縣北港鎮",
    "工廠負責人姓名": "蔡林美女",
    "營利事業統一編號": "70378554",
    "工廠組織型態": "股份有限公司",
    "工廠設立核准日期": "0811005",
    "工廠登記核准日期": "0811012",
    "工廠登記狀態": "生產中",
    "產業類別": [
        "22塑膠製品製造業"
    ],
    "主要產品": [
        "220塑膠製品"
    ],
    "egis": {
        "AddrOrg": "雲林縣北港鎮番溝里番溝５０號",
        "FactoryID": "99654524",
        "FactoryName": "田園股份有限公司",
        "faxno": "",
        "IndustryClass": "塑膠皮、板、管材製造業(2201)",
        "IndustryClass2": "塑膠製品製造業(22)",
        "material": "",
        "plantrep": "蔡林美女",
        "prodname": "ＥＶＡ發泡",
        "telno": "",
        "web": "",
        "X": "176496.23",
        "Y": "2613213.95"
    }
}