{
    "工廠名稱": "全瑩企業社",
    "工廠登記編號": "99650461",
    "工廠設立許可案號": "08610007233326",
    "工廠地址": "彰化縣埔鹽鄉埔鹽村中正路五二號",
    "工廠市鎮鄉村里": "彰化縣埔鹽鄉埔鹽村",
    "工廠負責人姓名": "洪　秀　霞　",
    "營利事業統一編號": "05930383",
    "工廠組織型態": "獨資",
    "工廠設立核准日期": "0861222",
    "工廠登記核准日期": "0870121",
    "工廠登記狀態": "生產中",
    "產業類別": [
        "15紙漿、紙及紙製品製造業",
        "22塑膠製品製造業"
    ],
    "主要產品": [
        "152紙容器",
        "220塑膠製品"
    ],
    "egis": {
        "AddrOrg": "彰化縣埔鹽鄉埔鹽村中正路５２號",
        "FactoryID": "99650461",
        "FactoryName": "全瑩企業社",
        "faxno": "",
        "IndustryClass": "塑膠膜袋製造業(2202)",
        "IndustryClass2": "塑膠製品製造業(22)",
        "material": "",
        "plantrep": "洪秀霞",
        "prodname": "纖維編織袋",
        "telno": "04-8653936",
        "web": "",
        "X": "196602.00",
        "Y": "2654763.79"
    }
}