{
    "工廠名稱": "鑫水企業股份有限公司二廠",
    "工廠登記編號": "99656609",
    "工廠設立許可案號": "07910000172815",
    "工廠地址": "臺南市仁德區保安里開發二路6號1樓A區、2樓",
    "工廠市鎮鄉村里": "臺南市仁德區保安里",
    "工廠負責人姓名": "陳文元　　　",
    "營利事業統一編號": "22058645",
    "工廠組織型態": "股份有限公司",
    "工廠設立核准日期": "0790627",
    "工廠登記核准日期": "0830126",
    "工廠登記狀態": "生產中",
    "產業類別": [
        "28電力設備製造業"
    ],
    "主要產品": [
        "285家用電器"
    ],
    "egis": {
        "AddrOrg": "臺南市仁德區保安里開發二路６號１樓Ａ區、２樓",
        "FactoryID": "99656609",
        "FactoryName": "鑫水企業股份有限公司二廠",
        "faxno": "",
        "IndustryClass": "家用電扇製造業(2854)",
        "IndustryClass2": "電力設備製造業(28)",
        "material": "",
        "plantrep": "陳文元",
        "prodname": "電扇、電暖器",
        "telno": "06-2661477",
        "web": "",
        "X": "172627.57",
        "Y": "2535865.02"
    }
}