{
    "工廠名稱": "宏盛食品工業股份有限公司",
    "工廠登記編號": "99654175",
    "工廠設立許可案號": "08610000807384",
    "工廠地址": "雲林縣西螺鎮正興里光復西路八二之一號一樓",
    "工廠市鎮鄉村里": "雲林縣西螺鎮",
    "工廠負責人姓名": "吳美瑟",
    "營利事業統一編號": "23367486",
    "工廠組織型態": "股份有限公司",
    "工廠設立核准日期": "0860821",
    "工廠登記核准日期": "0861009",
    "工廠登記狀態": "生產中",
    "產業類別": [
        "08食品製造業"
    ],
    "主要產品": [
        "089其他食品"
    ],
    "egis": {
        "AddrOrg": "雲林縣西螺鎮正興里光復西路８２之１號１樓",
        "FactoryID": "99654175",
        "FactoryName": "宏盛食品工業股份有限公司",
        "faxno": "",
        "IndustryClass": "烘焙炊蒸食品製造業(0891)",
        "IndustryClass2": "食品製造業(08)",
        "material": "",
        "plantrep": "吳美瑟",
        "prodname": "粉圓，湯圓",
        "telno": "",
        "web": "",
        "X": "195289.00",
        "Y": "2632658.19"
    }
}