{
    "工廠名稱": "妙春實業股份有限公司",
    "工廠登記編號": "99669227",
    "工廠設立許可案號": "07410000161775",
    "工廠地址": "臺中市南屯區寶山里工業區二十四路4號",
    "工廠市鎮鄉村里": "臺中市南屯區寶山里",
    "工廠負責人姓名": "高美蘭",
    "營利事業統一編號": "22907416",
    "工廠組織型態": "股份有限公司",
    "工廠設立核准日期": "0740610",
    "工廠登記核准日期": "0750414",
    "工廠登記狀態": "生產中",
    "產業類別": [
        "19化學製品製造業"
    ],
    "主要產品": [
        "199其他化學製品"
    ],
    "egis": {
        "AddrOrg": "臺中市南屯區寶山里工業區二十四路４號",
        "FactoryID": "99669227",
        "FactoryName": "妙春實業股份有限公司",
        "faxno": "04-23593163",
        "IndustryClass": "其他化學製品製造業(1990)",
        "IndustryClass2": "化學製品製造業(19)",
        "material": "",
        "plantrep": "高美蘭",
        "prodname": "塑膠抗氧化劑",
        "telno": "04-23592448",
        "web": "www.everspringchem.com",
        "X": "209754.02",
        "Y": "2673246.61"
    }
}