{
    "工廠名稱": "良星企業股份有限公司",
    "工廠登記編號": "99666417",
    "工廠設立許可案號": "",
    "工廠地址": "臺東縣臺東市中興路三段五四八之一號",
    "工廠市鎮鄉村里": "臺東縣臺東市豐年里",
    "工廠負責人姓名": "許文良",
    "營利事業統一編號": "93710961",
    "工廠組織型態": "股份有限公司",
    "工廠設立核准日期": "",
    "工廠登記核准日期": "0700427",
    "工廠登記狀態": "生產中",
    "產業類別": [
        "08食品製造業"
    ],
    "主要產品": [
        "083蔬果處理及其製品"
    ],
    "egis": {
        "AddrOrg": "臺東縣臺東市中興路三段５４８之１號",
        "FactoryID": "99666417",
        "FactoryName": "良星企業股份有限公司",
        "faxno": "",
        "IndustryClass": "蔬果製品製造業(0832)",
        "IndustryClass2": "食品製造業(08)",
        "material": "",
        "plantrep": "許文良",
        "prodname": "鹽漬蔬果，梅胚",
        "telno": "089-227798",
        "web": "",
        "X": "261013.81",
        "Y": "2519078.46"
    }
}