{
    "工廠名稱": "錦興洋傘工業有限公司",
    "工廠登記編號": "99668214",
    "工廠設立許可案號": "06310000173625",
    "工廠地址": "新竹市復中里中央路三○九巷三六號",
    "工廠市鎮鄉村里": "新竹市東區復中里",
    "工廠負責人姓名": "王奕斌　　　",
    "營利事業統一編號": "47032165",
    "工廠組織型態": "有限公司",
    "工廠設立核准日期": "0631211",
    "工廠登記核准日期": "0780117",
    "工廠登記狀態": "生產中",
    "產業類別": [
        "33其他製造業"
    ],
    "主要產品": [
        "339其他製品"
    ],
    "egis": {
        "AddrOrg": "新竹市東區復中里中央路３０９巷３６號",
        "FactoryID": "99668214",
        "FactoryName": "錦興洋傘工業有限公司",
        "faxno": "03-5323109",
        "IndustryClass": "其他未分類製造業(3399)",
        "IndustryClass2": "其他製造業(33)",
        "material": "",
        "plantrep": "王奕斌",
        "prodname": "洋傘，傘骨",
        "telno": "03-5323105",
        "web": "",
        "X": "247776.90",
        "Y": "2744911.09"
    }
}