{
    "工廠名稱": "東銳精密有限公司",
    "工廠登記編號": "99679968",
    "工廠設立許可案號": "",
    "工廠地址": "彰化縣溪湖鎮西溪里工業路８號",
    "工廠市鎮鄉村里": "彰化縣溪湖鎮西溪里",
    "工廠負責人姓名": "陳督佑",
    "營利事業統一編號": "28056617",
    "工廠組織型態": "有限公司",
    "工廠設立核准日期": "",
    "工廠登記核准日期": "0950123",
    "工廠登記狀態": "生產中",
    "產業類別": [
        "25金屬製品製造業"
    ],
    "主要產品": [
        "251金屬手工具及模具",
        "259其他金屬製品"
    ],
    "egis": {
        "AddrOrg": "彰化縣溪湖鎮西溪里工業路８號",
        "FactoryID": "99679968",
        "FactoryName": "東銳精密有限公司",
        "faxno": "",
        "IndustryClass": "未分類其他金屬製品製造業(2599)",
        "IndustryClass2": "金屬製品製造業(25)",
        "material": "",
        "plantrep": "陳督佑",
        "prodname": "各種五金零件",
        "telno": "04-8853999",
        "web": "",
        "X": "197628.36",
        "Y": "2650029.74"
    }
}