{
    "工廠名稱": "鉦銓工業有限公司",
    "工廠登記編號": "99670202",
    "工廠設立許可案號": "08210019001403",
    "工廠地址": "臺中市南屯區中和里楓和路860號",
    "工廠市鎮鄉村里": "臺中市南屯區中和里",
    "工廠負責人姓名": "簡清風",
    "營利事業統一編號": "84348259",
    "工廠組織型態": "有限公司",
    "工廠設立核准日期": "0820707",
    "工廠登記核准日期": "0820803",
    "工廠登記狀態": "生產中",
    "產業類別": [
        "30汽車及其零件製造業",
        "31其他運輸工具及其零件製造業"
    ],
    "主要產品": [
        "303汽車零件",
        "312機車及其零件",
        "313自行車及其零件"
    ],
    "egis": {
        "AddrOrg": "臺中市南屯區中和里楓和路８６０號",
        "FactoryID": "99670202",
        "FactoryName": "鉦銓工業有限公司",
        "faxno": "04-24791272",
        "IndustryClass": "未分類其他運輸工具及其零件製造業(3190)",
        "IndustryClass2": "其他運輸工具及其零件製造業(31)",
        "material": "",
        "plantrep": "簡清風",
        "prodname": "旗竿，冰杓",
        "telno": "",
        "web": "",
        "X": "212027.01",
        "Y": "2668146.47"
    }
}