{
    "工廠名稱": "賓威紙器有限公司分廠",
    "工廠登記編號": "99675348",
    "工廠設立許可案號": "07610021001598",
    "工廠地址": "臺南市南區郡南里永安街225號",
    "工廠市鎮鄉村里": "臺南市南區郡南里",
    "工廠負責人姓名": "蘇進順",
    "營利事業統一編號": "22082321",
    "工廠組織型態": "有限公司",
    "工廠設立核准日期": "0760904",
    "工廠登記核准日期": "0740603",
    "工廠登記狀態": "生產中",
    "產業類別": [
        "15紙漿、紙及紙製品製造業"
    ],
    "主要產品": [
        "152紙容器"
    ],
    "egis": {
        "AddrOrg": "臺南市南區郡南里永安街２２５號",
        "FactoryID": "99675348",
        "FactoryName": "賓威紙器有限公司分廠",
        "faxno": "",
        "IndustryClass": "紙容器製造業(1520)",
        "IndustryClass2": "紙漿、紙及紙製品製造業(15)",
        "material": "",
        "plantrep": "蘇進順",
        "prodname": "瓦楞紙箱加工",
        "telno": "06-2631930",
        "web": "",
        "X": "167400.00",
        "Y": "2540866.00"
    }
}