{
    "工廠名稱": "金德裕食品廠",
    "工廠登記編號": "99674419",
    "工廠設立許可案號": "06410000126375",
    "工廠地址": "臺南市東區虎尾里裕信路398號",
    "工廠市鎮鄉村里": "臺南市東區虎尾里",
    "工廠負責人姓名": "石亨裕",
    "營利事業統一編號": "69796480",
    "工廠組織型態": "獨資",
    "工廠設立核准日期": "0640911",
    "工廠登記核准日期": "0650113",
    "工廠登記狀態": "生產中",
    "產業類別": [
        "08食品製造業"
    ],
    "主要產品": [
        "083蔬果處理及其製品",
        "089其他食品"
    ],
    "egis": {
        "AddrOrg": "臺南市東區虎尾里裕信路３９８號",
        "FactoryID": "99674419",
        "FactoryName": "金德裕食品廠",
        "faxno": "",
        "IndustryClass": "調味品製造業(0896)",
        "IndustryClass2": "食品製造業(08)",
        "material": "",
        "plantrep": "石亨裕",
        "prodname": "清醋、烏醋",
        "telno": "",
        "web": "",
        "X": "172560.39",
        "Y": "2542011.89"
    }
}