{
    "工廠名稱": "金泉成機械廠",
    "工廠登記編號": "99672073",
    "工廠設立許可案號": "07410019001522",
    "工廠地址": "臺中市東區旱溪里旱溪二街7號",
    "工廠市鎮鄉村里": "臺中市東區旱溪里",
    "工廠負責人姓名": "李秋鋒",
    "營利事業統一編號": "06054707",
    "工廠組織型態": "獨資",
    "工廠設立核准日期": "0740524",
    "工廠登記核准日期": "0740604",
    "工廠登記狀態": "生產中",
    "產業類別": [
        "29機械設備製造業"
    ],
    "主要產品": [
        "293通用機械設備"
    ],
    "egis": {
        "AddrOrg": "臺中市東區旱溪里旱溪二街７號",
        "FactoryID": "99672073",
        "FactoryName": "金泉成機械廠",
        "faxno": "",
        "IndustryClass": "其他通用機械設備製造業(2939)",
        "IndustryClass2": "機械設備製造業(29)",
        "material": "",
        "plantrep": "李秋鋒",
        "prodname": "機械設備",
        "telno": "",
        "web": "",
        "X": "219233.58",
        "Y": "2670745.50"
    }
}