{
    "工廠名稱": "銓勝塑膠實業有限公司",
    "工廠登記編號": "99674531",
    "工廠設立許可案號": "07710021001821",
    "工廠地址": "臺南市安南區新順里安和路2段318巷125弄96號",
    "工廠市鎮鄉村里": "臺南市安南區新順里",
    "工廠負責人姓名": "吳水樹",
    "營利事業統一編號": "69808090",
    "工廠組織型態": "有限公司",
    "工廠設立核准日期": "0771206",
    "工廠登記核准日期": "0790309",
    "工廠登記狀態": "生產中",
    "產業類別": [
        "22塑膠製品製造業"
    ],
    "主要產品": [
        "220塑膠製品"
    ],
    "egis": {
        "AddrOrg": "臺南市安南區新順里安和路二段３１８巷１２５弄９６號",
        "FactoryID": "99674531",
        "FactoryName": "銓勝塑膠實業有限公司",
        "faxno": "",
        "IndustryClass": "其他塑膠製品製造業(2209)",
        "IndustryClass2": "塑膠製品製造業(22)",
        "material": "",
        "plantrep": "吳水樹",
        "prodname": "ＰＶＣ盒、ＰＳ盒",
        "telno": "",
        "web": "",
        "X": "170087.84",
        "Y": "2549435.98"
    }
}