{
    "工廠名稱": "北大化工有限公司龜山廠",
    "工廠登記編號": "99688217",
    "工廠設立許可案號": "",
    "工廠地址": "桃園市龜山區大崗里頂湖路９２號",
    "工廠市鎮鄉村里": "桃園市龜山區大崗里",
    "工廠負責人姓名": "陳絲玲",
    "營利事業統一編號": "86582954",
    "工廠組織型態": "有限公司",
    "工廠設立核准日期": "",
    "工廠登記核准日期": "0940203",
    "工廠登記狀態": "生產中",
    "產業類別": [
        "19化學製品製造業"
    ],
    "主要產品": [
        "199其他化學製品"
    ],
    "egis": {
        "AddrOrg": "桃園市龜山區大崗里頂湖路９２號",
        "FactoryID": "99688217",
        "FactoryName": "北大化工有限公司龜山廠",
        "faxno": "03-3962552",
        "IndustryClass": "合成樹脂及塑膠製造業(1841)",
        "IndustryClass2": "化學材料製造業(18)",
        "material": "助劑、樹脂、增稠劑",
        "plantrep": "陳絲玲",
        "prodname": "樹脂",
        "telno": "03-3961197",
        "web": "www.beta-chem.com.tw",
        "X": "286962.73",
        "Y": "2769608.71"
    }
}