{
    "工廠名稱": "温信塑膠股份有限公司",
    "工廠登記編號": "99686494",
    "工廠設立許可案號": "07910003051042",
    "工廠地址": "桃園市大園區五權里五青路１３２號",
    "工廠市鎮鄉村里": "桃園市大園區五權里",
    "工廠負責人姓名": "温火連　　",
    "營利事業統一編號": "23696728",
    "工廠組織型態": "股份有限公司",
    "工廠設立核准日期": "0790503",
    "工廠登記核准日期": "0790530",
    "工廠登記狀態": "生產中",
    "產業類別": [
        "22塑膠製品製造業"
    ],
    "主要產品": [
        "220塑膠製品"
    ],
    "egis": {
        "AddrOrg": "桃園市大園區五權里五青路１３２號",
        "FactoryID": "99686494",
        "FactoryName": "?信塑膠股份有限公司",
        "faxno": "",
        "IndustryClass": "塑膠膜袋製造業(2202)",
        "IndustryClass2": "塑膠製品製造業(22)",
        "material": "",
        "plantrep": "?火連",
        "prodname": "塑膠袋",
        "telno": "",
        "web": "",
        "X": "273902.07",
        "Y": "2768119.76"
    }
}