{
    "工廠名稱": "正鑫福金屬有限公司",
    "工廠登記編號": "99697083",
    "工廠設立許可案號": "",
    "工廠地址": "新北市樹林區三俊街八五巷八號",
    "工廠市鎮鄉村里": "新北市樹林區",
    "工廠負責人姓名": "龍秀紅",
    "營利事業統一編號": "84385015",
    "工廠組織型態": "有限公司",
    "工廠設立核准日期": "",
    "工廠登記核准日期": "0961015",
    "工廠登記狀態": "生產中",
    "產業類別": [
        "25金屬製品製造業"
    ],
    "主要產品": [
        "252金屬結構及建築組件"
    ],
    "egis": {
        "AddrOrg": "新北市樹林區三俊街８５巷８號",
        "FactoryID": "99697083",
        "FactoryName": "正鑫福金屬有限公司",
        "faxno": "",
        "IndustryClass": "未分類其他金屬製品製造業(2599)",
        "IndustryClass2": "金屬製品製造業(25)",
        "material": "",
        "plantrep": "龍秀紅",
        "prodname": "不銹鋼扶手",
        "telno": "02-26763833",
        "web": "",
        "X": "292013.88",
        "Y": "2767605.69"
    }
}