{
    "工廠名稱": "立康生物科技股份有限公司宜蘭龍德廠",
    "工廠登記編號": "99706155",
    "工廠設立許可案號": "",
    "工廠地址": "宜蘭縣冬山鄉大興村德興六路26號",
    "工廠市鎮鄉村里": "宜蘭縣冬山鄉大興村",
    "工廠負責人姓名": "王梅薰",
    "營利事業統一編號": "73715670",
    "工廠組織型態": "股份有限公司",
    "工廠設立核准日期": "",
    "工廠登記核准日期": "0950113",
    "工廠登記狀態": "生產中",
    "產業類別": [
        "20藥品及醫用化學製品製造業"
    ],
    "主要產品": [
        "200藥品及醫用化學製品"
    ],
    "egis": {
        "AddrOrg": "宜蘭縣冬山鄉大興村德興六路２６號",
        "FactoryID": "99706155",
        "FactoryName": "良濟堂生技製藥有限公司宜蘭廠",
        "faxno": "",
        "IndustryClass": "中藥製造業(2004)",
        "IndustryClass2": "藥品及醫用化學製品製造業(20)",
        "material": "",
        "plantrep": "蔡憲璋",
        "prodname": "救苦丹、清血丸",
        "telno": "03-9904558",
        "web": "",
        "X": "332865.67",
        "Y": "2725144.59"
    }
}