{
    "工廠名稱": "劦茂金屬股份有限公司二廠",
    "工廠登記編號": "99705084",
    "工廠設立許可案號": "",
    "工廠地址": "高雄市岡山區本洲里本工西路２號",
    "工廠市鎮鄉村里": "高雄市岡山區本洲里",
    "工廠負責人姓名": "沈泰隆",
    "營利事業統一編號": "86176787",
    "工廠組織型態": "股份有限公司",
    "工廠設立核准日期": "",
    "工廠登記核准日期": "0950801",
    "工廠登記狀態": "生產中",
    "產業類別": [
        "25金屬製品製造業"
    ],
    "主要產品": [
        "252金屬結構及建築組件"
    ],
    "egis": {
        "AddrOrg": "高雄市岡山區本洲里本工西路２號",
        "FactoryID": "99705084",
        "FactoryName": "劦茂金屬股份有限公司二廠",
        "faxno": "",
        "IndustryClass": "金屬建築組件製造業(2522)",
        "IndustryClass2": "金屬製品製造業(25)",
        "material": "",
        "plantrep": "沈泰隆",
        "prodname": "金屬結構及建築組件",
        "telno": "",
        "web": "",
        "X": "174389.16",
        "Y": "2523186.19"
    }
}