{
    "工廠名稱": "弘翔精密工業股份有限公司新莊廠",
    "工廠登記編號": "99725794",
    "工廠設立許可案號": "",
    "工廠地址": "新北市新莊區化成路382巷3號1樓",
    "工廠市鎮鄉村里": "新北市新莊區",
    "工廠負責人姓名": "王丹局",
    "營利事業統一編號": "80008996",
    "工廠組織型態": "股份有限公司",
    "工廠設立核准日期": "",
    "工廠登記核准日期": "0990528",
    "工廠登記狀態": "生產中",
    "產業類別": [
        "25金屬製品製造業",
        "29機械設備製造業"
    ],
    "主要產品": [
        "251金屬手工具及模具",
        "252金屬結構及建築組件",
        "291金屬加工用機械設備"
    ],
    "egis": {
        "AddrOrg": "新北市新莊區化成路３８２巷３號１樓",
        "FactoryID": "99725794",
        "FactoryName": "弘翔精密工業股份有限公司新莊廠",
        "faxno": "",
        "IndustryClass": "其他金屬加工處理業(2549)",
        "IndustryClass2": "金屬製品製造業(25)",
        "material": "",
        "plantrep": "王丹局",
        "prodname": "雷射切割",
        "telno": "02-29915714",
        "web": "",
        "X": "297068.25",
        "Y": "2771410.65"
    }
}