{
    "工廠名稱": "中環科技事業股份有限公司",
    "工廠登記編號": "64006051",
    "工廠設立許可案號": "",
    "工廠地址": "高雄市前鎮區信義里新衙路２８６之８號３樓之１",
    "工廠市鎮鄉村里": "高雄市前鎮區信義里",
    "工廠負責人姓名": "曾弘義",
    "營利事業統一編號": "23340163",
    "工廠組織型態": "股份有限公司",
    "工廠設立核准日期": "",
    "工廠登記核准日期": "0960518",
    "工廠登記狀態": "生產中",
    "產業類別": [
        "25金屬製品製造業"
    ],
    "主要產品": [
        "251金屬手工具及模具"
    ],
    "egis": {
        "AddrOrg": "高雄市前鎮區信義里新衙路２８６之８號３樓之１",
        "FactoryID": "64006051",
        "FactoryName": "中環科技事業股份有限公司",
        "faxno": "",
        "IndustryClass": "未分類其他金屬製品製造業(2599)",
        "IndustryClass2": "金屬製品製造業(25)",
        "material": "",
        "plantrep": "曾弘義",
        "prodname": "金屬鑽頭",
        "telno": "",
        "web": "",
        "X": "179674.42",
        "Y": "2498176.74"
    }
}