{
    "工廠名稱": "中國鋼鐵股份有限公司",
    "工廠登記編號": "64000249",
    "工廠設立許可案號": "6164131091",
    "工廠地址": "高雄市小港區鳳宮里中鋼路１號、高雄市小港區山明里東林路17號、高雄市小港區山明里大業南路３８號、高雄市小港區鳳鳴里沿海三路５６號",
    "工廠市鎮鄉村里": "高雄市小港區鳳宮里",
    "工廠負責人姓名": "翁朝棟",
    "營利事業統一編號": "30414175",
    "工廠組織型態": "股份有限公司",
    "工廠設立核准日期": "0611212",
    "工廠登記核准日期": "0670717",
    "工廠登記狀態": "生產中",
    "產業類別": [
        "14木竹製品製造業",
        "17石油及煤製品製造業",
        "18化學材料製造業",
        "19化學製品製造業",
        "21橡膠製品製造業",
        "23非金屬礦物製品製造業",
        "24基本金屬製造業",
        "25金屬製品製造業",
        "28電力設備製造業",
        "29機械設備製造業",
        "30汽車及其零件製造業",
        "31其他運輸工具及其零件製造業",
        "33其他製造業"
    ],
    "主要產品": [
        "140木竹製品",
        "170石油及煤製品",
        "181基本化學材料",
        "199其他化學製品",
        "210橡膠製品",
        "232耐火、黏土建築材料及陶瓷製品",
        "239其他非金屬礦物製品",
        "241鋼鐵",
        "242鋁",
        "243銅",
        "249其他基本金屬",
        "251金屬手工具及模具",
        "252金屬結構及建築組件",
        "253金屬容器",
        "254金屬加工處理",
        "281發電、輸電、配電機械",
        "283電線及配線器材",
        "289其他電力設備",
        "291金屬加工用機械設備",
        "292其他專用機械設備",
        "293通用機械設備",
        "301汽車",
        "302車體",
        "303汽車零件",
        "319未分類其他運輸工具及其零件",
        "339其他製品"
    ]
}