{
    "工廠名稱": "嘉弈有限公司",
    "工廠登記編號": "65002779",
    "工廠設立許可案號": "",
    "工廠地址": "新北市三重區光復路2段126巷35號1樓",
    "工廠市鎮鄉村里": "新北市三重區",
    "工廠負責人姓名": "王建興",
    "營利事業統一編號": "89323209",
    "工廠組織型態": "有限公司",
    "工廠設立核准日期": "",
    "工廠登記核准日期": "1030115",
    "工廠登記狀態": "生產中",
    "產業類別": [
        "25金屬製品製造業"
    ],
    "主要產品": [
        "251金屬手工具及模具"
    ],
    "egis": {
        "AddrOrg": "新北市三重區光復路二段１２６巷３５號１樓",
        "FactoryID": "65002779",
        "FactoryName": "嘉弈有限公司",
        "faxno": "",
        "IndustryClass": "未分類其他金屬製品製造業(2599)",
        "IndustryClass2": "金屬製品製造業(25)",
        "material": "",
        "plantrep": "王建興",
        "prodname": "金屬手工具及模具",
        "telno": "",
        "web": "",
        "X": "297447.92",
        "Y": "2772377.41"
    }
}