{
    "工廠名稱": "金富針織有限公司",
    "工廠登記編號": "65000508",
    "工廠設立許可案號": "",
    "工廠地址": "新北市土城區中央路3段126巷25弄3號1樓",
    "工廠市鎮鄉村里": "新北市土城區",
    "工廠負責人姓名": "賴金福",
    "營利事業統一編號": "53415154",
    "工廠組織型態": "有限公司",
    "工廠設立核准日期": "",
    "工廠登記核准日期": "1000623",
    "工廠登記狀態": "生產中",
    "產業類別": [
        "11紡織業",
        "12成衣及服飾品製造業"
    ],
    "主要產品": [
        "111紡紗",
        "112織布",
        "113不織布",
        "115紡織品",
        "121梭織成衣",
        "122針織成衣"
    ],
    "egis": {
        "AddrOrg": "新北市土城區中央路三段１２６巷２５弄３號１樓",
        "FactoryID": "65000508",
        "FactoryName": "金富針織有限公司",
        "faxno": "",
        "IndustryClass": "針織內衣及睡衣製造業(1222)",
        "IndustryClass2": "成衣及服飾品製造業(12)",
        "material": "",
        "plantrep": "賴金福",
        "prodname": "針織代工",
        "telno": "",
        "web": "",
        "X": "293830.72",
        "Y": "2762309.98"
    }
}