{
    "工廠名稱": "大圓美術有限公司",
    "工廠登記編號": "65001279",
    "工廠設立許可案號": "",
    "工廠地址": "新北市汐止區環河街82號1樓",
    "工廠市鎮鄉村里": "新北市汐止區",
    "工廠負責人姓名": "何許秋蘭",
    "營利事業統一編號": "84524261",
    "工廠組織型態": "有限公司",
    "工廠設立核准日期": "",
    "工廠登記核准日期": "1010417",
    "工廠登記狀態": "生產中",
    "產業類別": [
        "16印刷及資料儲存媒體複製業"
    ],
    "主要產品": [
        "161印刷及其輔助"
    ],
    "egis": {
        "AddrOrg": "新北市汐止區環河街８２號１樓",
        "FactoryID": "65001279",
        "FactoryName": "大圓美術有限公司",
        "faxno": "",
        "IndustryClass": "紙張製造業(1512)",
        "IndustryClass2": "紙漿、紙及紙製品製造業(15)",
        "material": "",
        "plantrep": "何許秋蘭",
        "prodname": "紙張",
        "telno": "",
        "web": "",
        "X": "313577.39",
        "Y": "2772661.27"
    }
}