{
    "工廠名稱": "傑斌企業股份有限公司",
    "工廠登記編號": "66001702",
    "工廠設立許可案號": "",
    "工廠地址": "臺中市神岡區豐洲里前寮路9號",
    "工廠市鎮鄉村里": "臺中市神岡區豐洲里",
    "工廠負責人姓名": "潘世欽",
    "營利事業統一編號": "23707719",
    "工廠組織型態": "股份有限公司",
    "工廠設立核准日期": "",
    "工廠登記核准日期": "1020315",
    "工廠登記狀態": "生產中",
    "產業類別": [
        "33其他製造業"
    ],
    "主要產品": [
        "331育樂用品"
    ],
    "egis": {
        "AddrOrg": "臺中市神岡區豐洲里前寮路９號",
        "FactoryID": "66001702",
        "FactoryName": "傑斌企業股份有限公司",
        "faxno": "",
        "IndustryClass": "體育用品製造業(3311)",
        "IndustryClass2": "其他製造業(33)",
        "material": "",
        "plantrep": "潘世欽",
        "prodname": "眼膏．手套修補器．眼貼．止滑粉",
        "telno": "04-25270289",
        "web": "",
        "X": "220008.08",
        "Y": "2683979.79"
    }
}