{
    "工廠名稱": "順盟科技有限公司永康廠",
    "工廠登記編號": "67001152",
    "工廠設立許可案號": "",
    "工廠地址": "臺南市永康區塩洲里洲工街145巷15號",
    "工廠市鎮鄉村里": "臺南市永康區塩洲里",
    "工廠負責人姓名": "陳盈州",
    "營利事業統一編號": "25015634",
    "工廠組織型態": "有限公司",
    "工廠設立核准日期": "",
    "工廠登記核准日期": "1040224",
    "工廠登記狀態": "生產中",
    "產業類別": [
        "28電力設備製造業",
        "30汽車及其零件製造業",
        "31其他運輸工具及其零件製造業"
    ],
    "主要產品": [
        "284照明設備",
        "303汽車零件",
        "312機車及其零件"
    ],
    "egis": {
        "AddrOrg": "臺南市永康區?洲里洲工街１４５巷１５號",
        "FactoryID": "67001152",
        "FactoryName": "順盟科技有限公司永康廠",
        "faxno": "",
        "IndustryClass": "照明器具製造業(2842)",
        "IndustryClass2": "電力設備製造業(28)",
        "material": "",
        "plantrep": "陳盈州",
        "prodname": "照明設備",
        "telno": "",
        "web": "",
        "X": "170604.51",
        "Y": "2548129.19"
    }
}